DeeperBin/Binning.py
DeeperBin/IO.py
DeeperBin/__init__.py
DeeperBin/logger.py
DeeperBin/main.py
DeeperBin/pretrain.py
DeeperBin/CallGenes/__init__.py
DeeperBin/CallGenes/gene_utils.py
DeeperBin/CallGenes/hmm_utils.py
DeeperBin/CallGenes/pfam.py
DeeperBin/Cluster/__init__.py
DeeperBin/Cluster/cluster.py
DeeperBin/Cluster/first_cluster.py
DeeperBin/Cluster/first_cluster_utils.py
DeeperBin/Cluster/sec_cluster.py
DeeperBin/Cluster/sec_cluster_utils.py
DeeperBin/Cluster/split_utils.py
DeeperBin/DataProcess/__init__.py
DeeperBin/DataProcess/data_utils.py
DeeperBin/Dereplication/__init__.py
DeeperBin/Dereplication/checkm_utils.py
DeeperBin/Dereplication/galah_utils.py
DeeperBin/Model/__init__.py
DeeperBin/Model/model.py
DeeperBin/Seqs/__init__.py
DeeperBin/Seqs/seq_info.py
DeeperBin/Seqs/seq_utils.py
DeeperBin/Trainer/__init__.py
DeeperBin/Trainer/dataset.py
DeeperBin/Trainer/loss.py
DeeperBin/Trainer/ssmt.py
DeeperBin/Trainer/trainer.py
DeeperBin/Trainer/warmup.py
DeeperBin-1.0.7.dist-info/LICENSE
DeeperBin-1.0.7.dist-info/METADATA
DeeperBin-1.0.7.dist-info/WHEEL
DeeperBin-1.0.7.dist-info/entry_points.txt
DeeperBin-1.0.7.dist-info/top_level.txt
DeeperBin-1.0.7.dist-info/RECORD
