Metadata-Version: 2.1
Name: DeeperBin
Version: 1.0.7
Summary: The binner to cluster contigs.
Home-page: UNKNOWN
Author: Bohao Zou
Author-email: csbhzou@comp.hkbu.edu.hk
License: UNKNOWN
Platform: UNKNOWN
Requires-Python: >=3.9
License-File: LICENSE
Requires-Dist: psutil (==6.1.0)
